{"fname":"cs.webdev.frontend.language.js.jsframework.react.test.tools.react-testing-library.finding-elements","stub":true,"vault":{"fsPath":"vault"},"schemaStub":false,"type":"note","updated":1664879699721,"created":1664879699721,"id":"qwfv2kevv4oxjas3rf2ml7d","desc":"","links":[],"anchors":{},"children":["c94usudbgkp1rmdytku1jox","mp77zy4z20zkh9ysbypn82m","juasj6stzaklgy589ka513r","duwl0sgnkwobbw1gxf6c1sd","zwv8tszsjunz4bevigdgfu0"],"parent":"oq3rav3t80a0b8py80pwfsv","data":{},"title":"Finding Elements"}
