{"id":"t0d3zvjj1iral5yg7ejib70","title":"Id","desc":"","updated":1657040807191,"created":1657034660354,"custom":{},"fname":"cs.webdev.frontend.language.css.selectors.id","type":"note","vault":{"fsPath":"vault"},"contentHash":"17807b0e5675c2b6b48b851af60a602b","links":[{"type":"wiki","from":{"fname":"cs.webdev.frontend.language.css.selectors.id","id":"t0d3zvjj1iral5yg7ejib70","vaultName":"vault"},"value":"cs.webdev.frontend.language.html","position":{"start":{"line":13,"column":149,"offset":304},"end":{"line":13,"column":185,"offset":340},"indent":[]},"xvault":false,"sameFile":false,"to":{"fname":"cs.webdev.frontend.language.html"}},{"type":"wiki","from":{"fname":"cs.webdev.frontend.language.css.selectors.id","id":"t0d3zvjj1iral5yg7ejib70","vaultName":"vault"},"value":"cs.webdev.frontend.language.js","position":{"start":{"line":13,"column":277,"offset":432},"end":{"line":13,"column":311,"offset":466},"indent":[]},"xvault":false,"sameFile":false,"to":{"fname":"cs.webdev.frontend.language.js"}}],"anchors":{},"children":[],"parent":"m89hehsy9w8xyn9hpqmdg5q","data":{}}
